napari_biomag_annotator/__init__.py
napari_biomag_annotator/_reader.py
napari_biomag_annotator/_version.py
napari_biomag_annotator/_widget.py
napari_biomag_annotator/_writer.py
napari_biomag_annotator/install.bat
napari_biomag_annotator/install.sh
napari_biomag_annotator/napari.yaml
napari_biomag_annotator/startup_napari.bat
napari_biomag_annotator/startup_napari.sh
napari_biomag_annotator/_tests/__init__.py
napari_biomag_annotator/_tests/test_reader.py
napari_biomag_annotator/_tests/test_widget.py
napari_biomag_annotator/_tests/test_writer.py
napari_biomag_annotator/icon/biomag-logo.png
napari_biomag_annotator-0.0.3.dist-info/LICENSE
napari_biomag_annotator-0.0.3.dist-info/METADATA
napari_biomag_annotator-0.0.3.dist-info/WHEEL
napari_biomag_annotator-0.0.3.dist-info/entry_points.txt
napari_biomag_annotator-0.0.3.dist-info/top_level.txt
napari_biomag_annotator-0.0.3.dist-info/RECORD
