Metadata-Version: 2.1
Name: napari-biomag-annotator
Version: 0.0.3
Summary: An annotator tool collection by the BIOMAG group.
Home-page: https://github.com/biomag-lab/napari-biomag-annotator
Author: Reka Hollandi, David Bauer
Author-email: hunreka93@hotmail.com
License: BSD-3-Clause
Project-URL: Bug Tracker, https://github.com/biomag-lab/napari-biomag-annotator/issues
Project-URL: Documentation, https://github.com/biomag-lab/napari-biomag-annotator#README.md
Project-URL: Source Code, https://github.com/biomag-lab/napari-biomag-annotator
Project-URL: User Support, https://github.com/biomag-lab/napari-biomag-annotator/issues
Classifier: Development Status :: 2 - Pre-Alpha
Classifier: Framework :: napari
Classifier: Intended Audience :: Developers
Classifier: License :: OSI Approved :: BSD License
Classifier: Operating System :: OS Independent
Classifier: Programming Language :: Python
Classifier: Programming Language :: Python :: 3
Classifier: Programming Language :: Python :: 3 :: Only
Classifier: Programming Language :: Python :: 3.8
Classifier: Programming Language :: Python :: 3.9
Classifier: Programming Language :: Python :: 3.10
Classifier: Topic :: Scientific/Engineering :: Image Processing
Requires-Python: >=3.8
License-File: LICENSE
Requires-Dist: napari
Requires-Dist: napari-plugin-engine >=0.1.4
Requires-Dist: napari-annotatorj
Requires-Dist: napari-nD-annotator
Provides-Extra: testing
Requires-Dist: tox ; extra == 'testing'
Requires-Dist: pytest ; extra == 'testing'
Requires-Dist: pytest-cov ; extra == 'testing'
Requires-Dist: pytest-qt ; extra == 'testing'
Requires-Dist: napari ; extra == 'testing'
Requires-Dist: pyqt5 ; extra == 'testing'
